pthr_db_caller/__init__.py
pthr_db_caller/config.py
pthr_db_caller/curation_status_model.py
pthr_db_caller/db_caller.py
pthr_db_caller/mod_id_mapper.py
pthr_db_caller/panther_tree_graph.py
pthr_db_caller/pthr_comment_helper.py
pthr_db_caller/taxon_validate.py
pthr_db_caller/models/__init__.py
pthr_db_caller/models/metadata.py
pthr_db_caller/models/orthoxml.py
pthr_db_caller/models/paint.py
pthr_db_caller/models/panther.py
pthr_db_caller/models/protein_class.py
pthr_db_caller/models/refprot_file.py
pthr_db_caller-2.0.2.data/scripts/align_taxon_term_table_species.py
pthr_db_caller-2.0.2.data/scripts/etree2orthoxml.py
pthr_db_caller-2.0.2.data/scripts/format_xml_iba_to_gaf.py
pthr_db_caller-2.0.2.data/scripts/merge_orthoxml.py
pthr_db_caller-2.0.2.data/scripts/pthrtree2newick.py
pthr_db_caller-2.0.2.data/scripts/taxon_term_tbl_lkp.py
pthr_db_caller-2.0.2.dist-info/METADATA
pthr_db_caller-2.0.2.dist-info/WHEEL
pthr_db_caller-2.0.2.dist-info/top_level.txt
pthr_db_caller-2.0.2.dist-info/RECORD
