Metadata-Version: 2.1
Name: pthr-db-caller
Version: 2.0.2
Summary: Python library for querying postgresl DBs and handling results tailored to PantherDB-related uses
Home-page: https://github.com/pantherdb/pthr_db_caller
Author: dustine32
Author-email: debert@usc.edu
License: UNKNOWN
Platform: UNKNOWN
Requires-Dist: psycopg2 >=2.9.9
Requires-Dist: PyYAML >=6.0.1
Requires-Dist: biopython >=1.73
Requires-Dist: ete3 >=3.1.2
Requires-Dist: matplotlib >=3.1.1
Requires-Dist: networkx >=2.7
Requires-Dist: lxml >=4.6.3
